AA20029UNO/Biseccion.py
AA20029UNO/Crammer.py
AA20029UNO/Descomposicion_LU.py
AA20029UNO/Gauss_Eliminacion.py
AA20029UNO/Gauss_Jordan.py
AA20029UNO/Gauss_Seidel.py
AA20029UNO/Jacobi.py
AA20029UNO/__init__.py
AA20029UNO/crammer_example.py
AA20029UNO/fraccion.py
AA20029UNO-0.1.4.dist-info/LICENSE.txt
AA20029UNO-0.1.4.dist-info/METADATA
AA20029UNO-0.1.4.dist-info/WHEEL
AA20029UNO-0.1.4.dist-info/top_level.txt
AA20029UNO-0.1.4.dist-info/RECORD
