Metadata-Version: 2.1
Name: AA20029UNO
Version: 0.1.4
Summary: Una librería para resolver sistemas de ecuaciones lineales y no lineales.
Home-page: https://github.com/Moises211
Author: Moises Aaron Alvarenga Acosta
Author-email: moisesacosta8@gmail.com
License: MIT
Platform: UNKNOWN
Classifier: License :: OSI Approved :: MIT License
Classifier: Programming Language :: Python :: 3
Classifier: Programming Language :: Python :: 3.7
Classifier: Programming Language :: Python :: 3.8
Classifier: Programming Language :: Python :: 3.9
Classifier: Programming Language :: Python :: 3.10
Classifier: Programming Language :: Python :: 3.11
Classifier: Programming Language :: Python :: 3.12
Classifier: Operating System :: OS Independent
License-File: LICENSE.txt
Requires-Dist: numpy>=1.10
